distkv_ext/owfs/__init__.py
distkv_ext/owfs/_config.yaml
distkv_ext/owfs/client.py
distkv_ext/owfs/mock.py
distkv_ext/owfs/model.py
distkv_ext/owfs/task.py
distkv_owfs-0.7.4.dist-info/METADATA
distkv_owfs-0.7.4.dist-info/WHEEL
distkv_owfs-0.7.4.dist-info/top_level.txt
distkv_owfs-0.7.4.dist-info/zip-safe
distkv_owfs-0.7.4.dist-info/RECORD
